{
  "session_id": "piwm_783",
  "persona": "和朋友一起逛商场便利区的年轻女性顾客，自己已经想买一份饮品但担心朋友觉得不划算。",
  "persona_visual": "26岁左右的女性，齐肩微卷黑发，穿米白色针织开衫和浅蓝色牛仔裤，斜挎一个棕色小包，手里拿着手机和细长钱包",
  "aida_stage": "desire",
  "bdi": {
    "belief": "她认为眼前的选择很适合自己现在想喝点东西的需求，但价格或必要性可能会被同行朋友质疑。",
    "desire": "她想买下自己喜欢的那一款，同时希望确认这个决定是合理的、不需要因为朋友看法而退缩。",
    "intention": "她倾向于再短暂确认一次后下定决心购买，但需要获得一种被认可和被鼓励的自信感。"
  },
  "observable_behavior": "她反复在正前方小范围扫视，手指轻轻摩挲钱包边缘，偶尔把手机抬起又放低，像是在比较后仍迟迟没有做出最终动作。",
  "facial_expression": "眉头微微收紧，嘴唇轻抿，眼神专注又犹豫，偶尔露出一点想买但不够坚定的迟疑表情。",
  "body_posture": "身体正面朝向镜头，上半身略微前倾，双肩有些收紧，双手始终停在胸前到腰部之间，姿态克制而不安定。",
  "timeline": {
    "t_0_2": "这位26岁左右的女性正面站定，微微前倾看向前方，双手握着手机和钱包，眼神很快被眼前的选择吸引。",
    "t_2_5": "她的视线在正前方左右小幅移动，手指反复摩挲钱包边缘，眉头轻轻皱起，像是在衡量自己是否真的应该买。",
    "t_5_8": "她短暂抬起手机又放低，嘴唇轻抿，眼睛向侧前方轻轻一瞥后立刻回到正前方，表现出担心同行朋友评价的犹豫。",
    "t_8_10": "她深吸一口气，肩膀稍微放松，双手把钱包握得更稳，表情从焦虑转为略微坚定，像是正在被说服去相信自己的决定。"
  }
}