{
  "session_id": "piwm_809",
  "persona": "刚走近设备的年轻女性，停在附近整理包带和手机。",
  "persona_visual": "24岁左右的女性，齐肩黑发，穿米白色衬衫和浅色半裙，手里拿着手机。",
  "aida_stage": "attention",
  "bdi": {
    "belief": "她还没有把当前注意力放到设备上。",
    "desire": "先整理好手里的物品。",
    "intention": "继续处理手头动作，之后再决定看向哪里。"
  },
  "observable_behavior": "她停在设备附近，一手整理包带，一手拿着手机，视线主要落在手部动作上。",
  "facial_expression": "表情自然平静，注意力在整理动作上。",
  "body_posture": "身体正面朝向镜头，站姿稳定但较为放松。",
  "timeline": {
    "t_0_2": "顾客走近并停在镜头中央。",
    "t_2_5": "她低头整理肩上的包带。",
    "t_5_8": "手里手机轻微调整，视线仍没有看向设备。",
    "t_8_10": "继续停留在设备附近，但注意力仍在手头事务上。"
  },
  "candidate_actions": [
    "hold_silent",
    "greet_open",
    "hold_ambient",
    "elicit_need_focus_open"
  ],
  "outcomes": {
    "hold_silent": {
      "next_aida_stage": "attention",
      "next_bdi": {
        "belief": "她仍不确定这台设备是否值得继续看。",
        "desire": "维持轻微好奇。",
        "intention": "停留意愿不稳定。"
      },
      "risk": "low",
      "benefit": "low",
      "delta_stage": 0.0,
      "delta_mental": 0.0,
      "rationale": "沉默不会造成负担，但很难把初步注意转成稳定兴趣。",
      "action_cost": 0.0,
      "preference_score": 0.0,
      "response_id": "hold_silent",
      "terminal_realization": {
        "surface_text": "",
        "screen": {
          "action": "idle_minimal",
          "cta": null
        },
        "voice_style": "silent",
        "light": "maintain_current_soft_breathing",
        "cabinet_motion": null,
        "duration_ms": 0
      }
    },
    "greet_open": {
      "next_aida_stage": "interest",
      "next_bdi": {
        "belief": "她感到设备欢迎自己停下来看。",
        "desire": "愿意继续了解这里有什么。",
        "intention": "开始把注意力稳定放到设备上。"
      },
      "risk": "low",
      "benefit": "high",
      "delta_stage": 0.3,
      "delta_mental": 0.34,
      "rationale": "友好开场与当前阶段最匹配，既轻量又能完成第一次转化。",
      "action_cost": 0.05,
      "preference_score": 0.28,
      "response_id": "greet_open",
      "terminal_realization": {
        "surface_text": "欢迎光临，您可以先随便看看。",
        "screen": {
          "action": "show_welcome",
          "cta": null
        },
        "voice_style": "warm",
        "light": "soft_welcome",
        "cabinet_motion": null,
        "duration_ms": 2500
      }
    },
    "hold_ambient": {
      "next_aida_stage": "attention",
      "next_bdi": {
        "belief": "设备不会主动施压。",
        "desire": "仍可按自己意愿决定是否继续。",
        "intention": "继续短暂观察。"
      },
      "risk": "very low",
      "benefit": "medium",
      "delta_stage": 0.05,
      "delta_mental": 0.1,
      "rationale": "舒适感提升有限，但不足以替代合时宜的首次欢迎。",
      "action_cost": 0.05,
      "preference_score": 0.060000000000000005,
      "response_id": "hold_ambient",
      "terminal_realization": {
        "surface_text": "您慢慢看，需要时我再帮您。",
        "screen": {
          "action": "return_to_attract_loop",
          "cta": null
        },
        "voice_style": "soft",
        "light": "ambient_low_attention",
        "cabinet_motion": null,
        "duration_ms": 2500
      }
    },
    "elicit_need_focus_open": {
      "next_aida_stage": "interest",
      "next_bdi": {
        "belief": "设备已经开始引导她思考需求。",
        "desire": "可能开始辨别关注点。",
        "intention": "愿意继续，但节奏稍被提前。"
      },
      "risk": "medium",
      "benefit": "medium",
      "delta_stage": 0.18,
      "delta_mental": 0.1,
      "rationale": "开放问题可以工作，但在刚注意阶段略显过早。",
      "action_cost": 0.2,
      "preference_score": 0.08199999999999999,
      "response_id": "elicit_need_focus_open",
      "terminal_realization": {
        "surface_text": "您今天想先看价格、功能，还是适合什么场景？",
        "screen": {
          "action": "show_choice_bubbles",
          "choices": [
            "价格",
            "功能",
            "场景"
          ],
          "cta": null
        },
        "voice_style": "curious",
        "light": "soft_invitation",
        "cabinet_motion": null,
        "duration_ms": 5000
      }
    }
  },
  "best_action": "greet_open",
  "response_id": "greet_open",
  "realization": {
    "surface_text": "欢迎光临，您可以先随便看看。",
    "screen": {
      "action": "show_welcome",
      "cta": null
    },
    "voice_style": "warm",
    "light": "soft_welcome",
    "cabinet_motion": null,
    "duration_ms": 2500
  },
  "score_weights": {
    "alpha": 0.4,
    "beta": 0.5,
    "gamma": 0.2
  }
}